{
  "plants": [
    {
      "id": "1",
      "name": "Basil",
      "climate_id": "1",
      "grow_directions": "Fill Chamber water reservoir with clean water, then put the water reservoir back inside the chamber and initiate pH balancing.",
      "day_of_cycle": "0"
    },
    {
      "id": "2",
      "name": "Tomatoes",
      "climate_id": "1",
      "grow_directions": "Fill Chamber water reservoir with clean water, then put the water reservoir back inside the chamber and initiate pH balancing.",
      "day_of_cycle": "0"
    }
  ],
  "climates": [
    {
      "id": "1",
      "type": "tropical",
      "given_settings": [
        {
          "temperature": "77",
          "humidity": "48",
          "pH": "5.7",
          "PPM": "345",
          "height": "0",
          "water": "85"
        }
      ]
    },
    {
      "id": "2",
      "type": "temperate",
      "given_settings": [
        {
          "temperature": "74",
          "humidity": "40",
          "pH": "5.7",
          "PPM": "345",
          "height": "0",
          "water": "85"
        }
      ]
    },
    {
      "id": "3",
      "type": "custom",
      "given_settings": [
        {
          "temperature": "0",
          "humidity": "0",
          "pH": "0",
          "PPM": "0",
          "height": "0",
          "water": "85"
        }
      ]
    }
  ],
  "sensor_data": [
    {
      "time": "2017-07-28 10:00:00.846621+00",
      "chamber_id": "1",
      "temperature": "77",
      "humidity": "50",
      "pH": "5.9",
      "PPM": "345",
      "height": "6",
      "water": "85",
      "photo": "na"
    },
    {
      "time": "2017-07-28 10:28:42.846621+00",
      "chamber_id": "1",
      "temperature": "77",
      "humidity": "50",
      "pH": null,
      "PPM": null,
      "height": null,
      "water": null,
      "photo": null
    },
    {
      "time": "2017-07-28 10:56:42.846621+00",
      "chamber_id": "1",
      "temperature": "77",
      "humidity": "50",
      "pH": null,
      "PPM": null,
      "height": null,
      "water": null,
      "photo": null
    },
    {
      "time": "2017-07-28 11:24:42.846621+00",
      "chamber_id": "1",
      "temperature": "77",
      "humidity": "50",
      "pH": null,
      "PPM": null,
      "height": null,
      "water": null,
      "photo": null
    },
    {
      "time": "2017-07-28 11:52:42.846621+00",
      "chamber_id": "1",
      "temperature": "78",
      "humidity": "50",
      "pH": null,
      "PPM": null,
      "height": null,
      "water": null,
      "photo": null
    },
    {
      "time": "2017-07-28 12:20:42.846621+00",
      "chamber_id": "1",
      "temperature": "77",
      "humidity": "50",
      "pH": null,
      "PPM": null,
      "height": null,
      "water": null,
      "photo": null
    },
    {
      "time": "2017-07-28 12:48:42.846621+00",
      "chamber_id": "1",
      "temperature": "77",
      "humidity": "50",
      "pH": null,
      "PPM": null,
      "height": null,
      "water": null,
      "photo": null
    },
    {
      "time": "2017-07-28 13:16:42.846621+00",
      "chamber_id": "1",
      "temperature": "77",
      "humidity": "50",
      "pH": null,
      "PPM": null,
      "height": null,
      "water": null,
      "photo": null
    },
    {
      "time": "2017-07-28 13:44:42.846621+00",
      "chamber_id": "1",
      "temperature": "77",
      "humidity": "50",
      "pH": null,
      "PPM": null,
      "height": null,
      "water": null,
      "photo": null
    },
    {
      "time": "2017-07-28 14:12:42.846621+00",
      "chamber_id": "1",
      "temperature": "77",
      "humidity": "50",
      "pH": null,
      "PPM": null,
      "height": null,
      "water": null,
      "photo": null
    },
    {
      "time": "2017-07-28 14:40:42.846621+00",
      "chamber_id": "1",
      "temperature": "77",
      "humidity": "50",
      "pH": null,
      "PPM": null,
      "height": null,
      "water": null,
      "photo": null
    },
    {
      "time": "2017-07-28 15:08:42.846621+00",
      "chamber_id": "1",
      "temperature": "77",
      "humidity": "50",
      "pH": null,
      "PPM": null,
      "height": null,
      "water": null,
      "photo": null
    },
    {
      "time": "2017-07-28 15:08:42.846621+00",
      "chamber_id": "1",
      "temperature": "77",
      "humidity": "50",
      "pH": null,
      "PPM": null,
      "height": null,
      "water": null,
      "photo": null
    },
    {
      "time": "2017-07-28 15:36:42.846621+00",
      "chamber_id": "1",
      "temperature": "77",
      "humidity": "50",
      "pH": null,
      "PPM": null,
      "height": null,
      "water": null,
      "photo": null
    },
    {
      "time": "2017-07-28 16:04:42.846621+00",
      "chamber_id": "1",
      "temperature": "77",
      "humidity": "50",
      "pH": "5.8",
      "PPM": null,
      "height": null,
      "water": null,
      "photo": "na"
    },
    {
      "time": "2017-07-28 16:32:42.846621+00",
      "chamber_id": "1",
      "temperature": "77",
      "humidity": "50",
      "pH": null,
      "PPM": null,
      "height": null,
      "water": null,
      "photo": null
    },
    {
      "time": "2017-07-28 17:00:42.846621+00",
      "chamber_id": "1",
      "temperature": "77",
      "humidity": "50",
      "pH": null,
      "PPM": null,
      "height": null,
      "water": null,
      "photo": null
    },
    {
      "time": "2017-07-28 17:28:42.846621+00",
      "chamber_id": "1",
      "temperature": "77",
      "humidity": "50",
      "pH": null,
      "PPM": null,
      "height": null,
      "water": null,
      "photo": null
    },
    {
      "time": "2017-07-28 17:56:42.846621+00",
      "chamber_id": "1",
      "temperature": "77",
      "humidity": "50",
      "pH": null,
      "PPM": null,
      "height": null,
      "water": null,
      "photo": null
    },
    {
      "time": "2017-07-28 18:24:42.846621+00",
      "chamber_id": "1",
      "temperature": "77",
      "humidity": "50",
      "pH": null,
      "PPM": null,
      "height": null,
      "water": null,
      "photo": null
    },
    {
      "time": "2017-07-28 18:52:42.846621+00",
      "chamber_id": "1",
      "temperature": "77",
      "humidity": "50",
      "pH": null,
      "PPM": null,
      "height": null,
      "water": null,
      "photo": null
    },
    {
      "time": "2017-07-28 19:20:42.846621+00",
      "chamber_id": "1",
      "temperature": "73",
      "humidity": "50",
      "pH": null,
      "PPM": null,
      "height": null,
      "water": null,
      "photo": null
    },
    {
      "time": "2017-07-28 19:48:42.846621+00",
      "chamber_id": "1",
      "temperature": "74",
      "humidity": "50",
      "pH": null,
      "PPM": null,
      "height": null,
      "water": null,
      "photo": null
    },
    {
      "time": "2017-07-28 20:16:42.846621+00",
      "chamber_id": "1",
      "temperature": "77",
      "humidity": "50",
      "pH": null,
      "PPM": null,
      "height": null,
      "water": null,
      "photo": null
    },
    {
      "time": "2017-07-28 20:44:42.846621+00",
      "chamber_id": "1",
      "temperature": "77",
      "humidity": "50",
      "pH": null,
      "PPM": null,
      "height": null,
      "water": null,
      "photo": null
    },
    {
      "time": "2017-07-28 21:12:42.846621+00",
      "chamber_id": "1",
      "temperature": "77",
      "humidity": "50",
      "pH": null,
      "PPM": null,
      "height": null,
      "water": null,
      "photo": null
    },
    {
      "time": "2017-07-28 21:40:42.846621+00",
      "chamber_id": "1",
      "temperature": "77",
      "humidity": "50",
      "pH": null,
      "PPM": null,
      "height": null,
      "water": null,
      "photo": null
    },
    {
      "time": "2017-07-28 22:08:42.846621+00",
      "chamber_id": "1",
      "temperature": "77",
      "humidity": "50",
      "pH": null,
      "PPM": null,
      "height": null,
      "water": null,
      "photo": null
    },
    {
      "time": "2017-07-28 22:36:42.846621+00",
      "chamber_id": "1",
      "temperature": "77",
      "humidity": "50",
      "pH": null,
      "PPM": null,
      "height": null,
      "water": null,
      "photo": null
    },
    {
      "time": "2017-07-28 23:04:42.846621+00",
      "chamber_id": "1",
      "temperature": "77",
      "humidity": "50",
      "pH": null,
      "PPM": null,
      "height": null,
      "water": null,
      "photo": null
    },
    {
      "time": "2017-07-28 23:32:42.846621+00",
      "chamber_id": "1",
      "temperature": "77",
      "humidity": "50",
      "pH": null,
      "PPM": null,
      "height": null,
      "water": null,
      "photo": null
    },
    {
      "time": "2017-07-29 00:00:42.846621+00",
      "chamber_id": "1",
      "temperature": "77",
      "humidity": "50",
      "pH": null,
      "PPM": null,
      "height": null,
      "water": null,
      "photo": null
    },
    {
      "time": "2017-07-29 00:28:42.846621+00",
      "chamber_id": "1",
      "temperature": "77",
      "humidity": "50",
      "pH": null,
      "PPM": null,
      "height": null,
      "water": null,
      "photo": null
    },
    {
      "time": "2017-07-29 00:56:42.846621+00",
      "chamber_id": "1",
      "temperature": "77",
      "humidity": "50",
      "pH": null,
      "PPM": null,
      "height": null,
      "water": null,
      "photo": null
    },
    {
      "time": "2017-07-29 01:24:42.846621+00",
      "chamber_id": "1",
      "temperature": "77",
      "humidity": "50",
      "pH": null,
      "PPM": null,
      "height": null,
      "water": null,
      "photo": null
    },
    {
      "time": "2017-07-29 01:52:42.846621+00",
      "chamber_id": "1",
      "temperature": "77",
      "humidity": "50",
      "pH": null,
      "PPM": null,
      "height": null,
      "water": null,
      "photo": null
    },
    {
      "time": "2017-07-29 02:20:42.846621+00",
      "chamber_id": "1",
      "temperature": "77",
      "humidity": "50",
      "pH": null,
      "PPM": null,
      "height": null,
      "water": null,
      "photo": null
    },
    {
      "time": "2017-07-29 02:48:42.846621+00",
      "chamber_id": "1",
      "temperature": "77",
      "humidity": "50",
      "pH": null,
      "PPM": null,
      "height": null,
      "water": null,
      "photo": null
    },
    {
      "time": "2017-07-29 03:16:42.846621+00",
      "chamber_id": "1",
      "temperature": "77",
      "humidity": "50",
      "pH": null,
      "PPM": null,
      "height": null,
      "water": null,
      "photo": null
    },
    {
      "time": "2017-07-29 03:16:42.846621+00",
      "chamber_id": "1",
      "temperature": "77",
      "humidity": "50",
      "pH": null,
      "PPM": null,
      "height": null,
      "water": null,
      "photo": null
    },
    {
      "time": "2017-07-29 03:44:42.846621+00",
      "chamber_id": "1",
      "temperature": "77",
      "humidity": "50",
      "pH": null,
      "PPM": null,
      "height": null,
      "water": null,
      "photo": null
    },
    {
      "time": "2017-07-29 04:12:42.846621+00",
      "chamber_id": "1",
      "temperature": "77",
      "humidity": "50",
      "pH": null,
      "PPM": null,
      "height": null,
      "water": null,
      "photo": null
    },
    {
      "time": "2017-07-29 04:40:42.846621+00",
      "chamber_id": "1",
      "temperature": "77",
      "humidity": "50",
      "pH": null,
      "PPM": null,
      "height": null,
      "water": null,
      "photo": null
    },
    {
      "time": "2017-07-29 05:08:42.846621+00",
      "chamber_id": "1",
      "temperature": "77",
      "humidity": "50",
      "pH": null,
      "PPM": null,
      "height": null,
      "water": null,
      "photo": null
    },
    {
      "time": "2017-07-29 05:36:42.846621+00",
      "chamber_id": "1",
      "temperature": "77",
      "humidity": "50",
      "pH": null,
      "PPM": null,
      "height": null,
      "water": null,
      "photo": null
    },
    {
      "time": "2017-07-29 06:04:42.846621+00",
      "chamber_id": "1",
      "temperature": "77",
      "humidity": "50",
      "pH": null,
      "PPM": null,
      "height": null,
      "water": null,
      "photo": null
    },
    {
      "time": "2017-07-29 06:32:42.846621+00",
      "chamber_id": "1",
      "temperature": "77",
      "humidity": "50",
      "pH": null,
      "PPM": null,
      "height": null,
      "water": null,
      "photo": null
    },
    {
      "time": "2017-07-29 07:00:42.846621+00",
      "chamber_id": "1",
      "temperature": "77",
      "humidity": "50",
      "pH": null,
      "PPM": null,
      "height": null,
      "water": null,
      "photo": null
    },
    {
      "time": "2017-07-29 07:28:42.846621+00",
      "chamber_id": "1",
      "temperature": "77",
      "humidity": "50",
      "pH": null,
      "PPM": null,
      "height": null,
      "water": null,
      "photo": null
    },
    {
      "time": "2017-07-29 07:56:42.846621+00",
      "chamber_id": "1",
      "temperature": "77",
      "humidity": "50",
      "pH": null,
      "PPM": null,
      "height": null,
      "water": null,
      "photo": null
    },
    {
      "time": "2017-07-29 08:24:42.846621+00",
      "chamber_id": "1",
      "temperature": "77",
      "humidity": "50",
      "pH": null,
      "PPM": null,
      "height": null,
      "water": null,
      "photo": null
    },
    {
      "time": "2017-07-29 08:52:42.846621+00",
      "chamber_id": "1",
      "temperature": "77",
      "humidity": "50",
      "pH": null,
      "PPM": null,
      "height": null,
      "water": null,
      "photo": null
    },
    {
      "time": "2017-07-29 09:20:42.846621+00",
      "chamber_id": "1",
      "temperature": "77",
      "humidity": "50",
      "pH": null,
      "PPM": null,
      "height": null,
      "water": null,
      "photo": null
    },
    {
      "time": "2017-07-29 09:48:42.846621+00",
      "chamber_id": "1",
      "temperature": "77",
      "humidity": "50",
      "pH": null,
      "PPM": null,
      "height": null,
      "water": null,
      "photo": null
    },
    {
      "time": "2017-07-29 10:00:00.846621+00",
      "chamber_id": "1",
      "temperature": "74",
      "humidity": "50",
      "pH": "5.9",
      "PPM": "350",
      "height": null,
      "water": null,
      "photo": "na"
    },
    {
      "time": "2017-07-29 10:28:42.846621+00",
      "chamber_id": "1",
      "temperature": "75",
      "humidity": "50",
      "pH": null,
      "PPM": null,
      "height": null,
      "water": null,
      "photo": null
    },
    {
      "time": "2017-07-29 10:56:42.846621+00",
      "chamber_id": "1",
      "temperature": "75",
      "humidity": "50",
      "pH": null,
      "PPM": null,
      "height": null,
      "water": null,
      "photo": null
    },
    {
      "time": "2017-07-29 11:24:42.846621+00",
      "chamber_id": "1",
      "temperature": "75",
      "humidity": "50",
      "pH": null,
      "PPM": null,
      "height": null,
      "water": null,
      "photo": null
    },
    {
      "time": "2017-07-29 11:52:42.846621+00",
      "chamber_id": "1",
      "temperature": "78",
      "humidity": "50",
      "pH": null,
      "PPM": null,
      "height": null,
      "water": null,
      "photo": null
    },
    {
      "time": "2017-07-29 12:20:42.846621+00",
      "chamber_id": "1",
      "temperature": "77",
      "humidity": "50",
      "pH": null,
      "PPM": null,
      "height": null,
      "water": null,
      "photo": null
    },
    {
      "time": "2017-07-29 12:48:42.846621+00",
      "chamber_id": "1",
      "temperature": "77",
      "humidity": "50",
      "pH": null,
      "PPM": null,
      "height": null,
      "water": null,
      "photo": null
    },
    {
      "time": "2017-07-29 13:16:42.846621+00",
      "chamber_id": "1",
      "temperature": "77",
      "humidity": "50",
      "pH": null,
      "PPM": null,
      "height": null,
      "water": null,
      "photo": null
    },
    {
      "time": "2017-07-29 13:44:42.846621+00",
      "chamber_id": "1",
      "temperature": "77",
      "humidity": "50",
      "pH": null,
      "PPM": null,
      "height": null,
      "water": null,
      "photo": null
    },
    {
      "time": "2017-07-29 14:12:42.846621+00",
      "chamber_id": "1",
      "temperature": "77",
      "humidity": "50",
      "pH": null,
      "PPM": null,
      "height": null,
      "water": null,
      "photo": null
    },
    {
      "time": "2017-07-29 14:40:42.846621+00",
      "chamber_id": "1",
      "temperature": "77",
      "humidity": "50",
      "pH": null,
      "PPM": null,
      "height": null,
      "water": null,
      "photo": null
    },
    {
      "time": "2017-07-29 15:08:42.846621+00",
      "chamber_id": "1",
      "temperature": "77",
      "humidity": "50",
      "pH": null,
      "PPM": null,
      "height": null,
      "water": null,
      "photo": null
    },
    {
      "time": "2017-07-29 15:08:42.846621+00",
      "chamber_id": "1",
      "temperature": "77",
      "humidity": "50",
      "pH": null,
      "PPM": null,
      "height": null,
      "water": null,
      "photo": null
    },
    {
      "time": "2017-07-29 15:36:42.846621+00",
      "chamber_id": "1",
      "temperature": "77",
      "humidity": "50",
      "pH": null,
      "PPM": null,
      "height": null,
      "water": null,
      "photo": null
    },
    {
      "time": "2017-07-29 16:04:42.846621+00",
      "chamber_id": "1",
      "temperature": "77",
      "humidity": "50",
      "pH": "5.8",
      "PPM": null,
      "height": null,
      "water": null,
      "photo": "na"
    },
    {
      "time": "2017-07-29 16:32:42.846621+00",
      "chamber_id": "1",
      "temperature": "77",
      "humidity": "50",
      "pH": null,
      "PPM": null,
      "height": null,
      "water": null,
      "photo": null
    },
    {
      "time": "2017-07-29 17:00:42.846621+00",
      "chamber_id": "1",
      "temperature": "77",
      "humidity": "50",
      "pH": null,
      "PPM": null,
      "height": null,
      "water": null,
      "photo": null
    },
    {
      "time": "2017-07-29 17:28:42.846621+00",
      "chamber_id": "1",
      "temperature": "77",
      "humidity": "50",
      "pH": null,
      "PPM": null,
      "height": null,
      "water": null,
      "photo": null
    },
    {
      "time": "2017-07-29 17:56:42.846621+00",
      "chamber_id": "1",
      "temperature": "77",
      "humidity": "50",
      "pH": null,
      "PPM": null,
      "height": null,
      "water": null,
      "photo": null
    },
    {
      "time": "2017-07-29 18:24:42.846621+00",
      "chamber_id": "1",
      "temperature": "77",
      "humidity": "50",
      "pH": null,
      "PPM": null,
      "height": null,
      "water": null,
      "photo": null
    },
    {
      "time": "2017-07-29 18:52:42.846621+00",
      "chamber_id": "1",
      "temperature": "77",
      "humidity": "50",
      "pH": null,
      "PPM": null,
      "height": null,
      "water": null,
      "photo": null
    },
    {
      "time": "2017-07-29 19:20:42.846621+00",
      "chamber_id": "1",
      "temperature": "73",
      "humidity": "50",
      "pH": null,
      "PPM": null,
      "height": null,
      "water": null,
      "photo": null
    },
    {
      "time": "2017-07-29 19:48:42.846621+00",
      "chamber_id": "1",
      "temperature": "74",
      "humidity": "50",
      "pH": null,
      "PPM": null,
      "height": null,
      "water": null,
      "photo": null
    },
    {
      "time": "2017-07-29 20:16:42.846621+00",
      "chamber_id": "1",
      "temperature": "77",
      "humidity": "50",
      "pH": null,
      "PPM": null,
      "height": null,
      "water": null,
      "photo": null
    },
    {
      "time": "2017-07-29 20:44:42.846621+00",
      "chamber_id": "1",
      "temperature": "77",
      "humidity": "50",
      "pH": null,
      "PPM": null,
      "height": null,
      "water": null,
      "photo": null
    },
    {
      "time": "2017-07-29 21:12:42.846621+00",
      "chamber_id": "1",
      "temperature": "77",
      "humidity": "50",
      "pH": null,
      "PPM": null,
      "height": null,
      "water": null,
      "photo": null
    },
    {
      "time": "2017-07-29 21:40:42.846621+00",
      "chamber_id": "1",
      "temperature": "77",
      "humidity": "50",
      "pH": null,
      "PPM": null,
      "height": null,
      "water": null,
      "photo": null
    },
    {
      "time": "2017-07-29 22:08:42.846621+00",
      "chamber_id": "1",
      "temperature": "77",
      "humidity": "50",
      "pH": null,
      "PPM": null,
      "height": null,
      "water": null,
      "photo": null
    },
    {
      "time": "2017-07-29 22:36:42.846621+00",
      "chamber_id": "1",
      "temperature": "77",
      "humidity": "50",
      "pH": null,
      "PPM": null,
      "height": null,
      "water": null,
      "photo": null
    },
    {
      "time": "2017-07-29 23:04:42.846621+00",
      "chamber_id": "1",
      "temperature": "77",
      "humidity": "50",
      "pH": null,
      "PPM": null,
      "height": null,
      "water": null,
      "photo": null
    },
    {
      "time": "2017-07-29 23:32:42.846621+00",
      "chamber_id": "1",
      "temperature": "77",
      "humidity": "50",
      "pH": null,
      "PPM": null,
      "height": null,
      "water": null,
      "photo": null
    },
    {
      "time": "2017-07-29 00:00:42.846621+00",
      "chamber_id": "1",
      "temperature": "77",
      "humidity": "50",
      "pH": null,
      "PPM": null,
      "height": null,
      "water": null,
      "photo": null
    },
    {
      "time": "2017-07-30 00:28:42.846621+00",
      "chamber_id": "1",
      "temperature": "77",
      "humidity": "50",
      "pH": null,
      "PPM": null,
      "height": null,
      "water": null,
      "photo": null
    },
    {
      "time": "2017-07-30 00:56:42.846621+00",
      "chamber_id": "1",
      "temperature": "77",
      "humidity": "50",
      "pH": null,
      "PPM": null,
      "height": null,
      "water": null,
      "photo": null
    },
    {
      "time": "2017-07-30 01:24:42.846621+00",
      "chamber_id": "1",
      "temperature": "77",
      "humidity": "50",
      "pH": null,
      "PPM": null,
      "height": null,
      "water": null,
      "photo": null
    },
    {
      "time": "2017-07-30 01:52:42.846621+00",
      "chamber_id": "1",
      "temperature": "77",
      "humidity": "50",
      "pH": null,
      "PPM": null,
      "height": null,
      "water": null,
      "photo": null
    },
    {
      "time": "2017-07-30 02:20:42.846621+00",
      "chamber_id": "1",
      "temperature": "77",
      "humidity": "50",
      "pH": null,
      "PPM": null,
      "height": null,
      "water": null,
      "photo": null
    },
    {
      "time": "2017-07-30 02:48:42.846621+00",
      "chamber_id": "1",
      "temperature": "77",
      "humidity": "50",
      "pH": null,
      "PPM": null,
      "height": null,
      "water": null,
      "photo": null
    },
    {
      "time": "2017-07-30 03:16:42.846621+00",
      "chamber_id": "1",
      "temperature": "77",
      "humidity": "50",
      "pH": null,
      "PPM": null,
      "height": null,
      "water": null,
      "photo": null
    },
    {
      "time": "2017-07-30 03:16:42.846621+00",
      "chamber_id": "1",
      "temperature": "77",
      "humidity": "50",
      "pH": null,
      "PPM": null,
      "height": null,
      "water": null,
      "photo": null
    },
    {
      "time": "2017-07-30 03:44:42.846621+00",
      "chamber_id": "1",
      "temperature": "77",
      "humidity": "50",
      "pH": null,
      "PPM": null,
      "height": null,
      "water": null,
      "photo": null
    },
    {
      "time": "2017-07-30 04:12:42.846621+00",
      "chamber_id": "1",
      "temperature": "77",
      "humidity": "50",
      "pH": null,
      "PPM": null,
      "height": null,
      "water": null,
      "photo": null
    },
    {
      "time": "2017-07-30 04:40:42.846621+00",
      "chamber_id": "1",
      "temperature": "77",
      "humidity": "50",
      "pH": null,
      "PPM": null,
      "height": null,
      "water": null,
      "photo": null
    },
    {
      "time": "2017-07-30 05:08:42.846621+00",
      "chamber_id": "1",
      "temperature": "77",
      "humidity": "50",
      "pH": null,
      "PPM": null,
      "height": null,
      "water": null,
      "photo": null
    },
    {
      "time": "2017-07-30 05:36:42.846621+00",
      "chamber_id": "1",
      "temperature": "77",
      "humidity": "50",
      "pH": null,
      "PPM": null,
      "height": null,
      "water": null,
      "photo": null
    },
    {
      "time": "2017-07-30 06:04:42.846621+00",
      "chamber_id": "1",
      "temperature": "77",
      "humidity": "50",
      "pH": null,
      "PPM": null,
      "height": null,
      "water": null,
      "photo": null
    },
    {
      "time": "2017-07-30 06:32:42.846621+00",
      "chamber_id": "1",
      "temperature": "77",
      "humidity": "50",
      "pH": null,
      "PPM": null,
      "height": null,
      "water": null,
      "photo": null
    },
    {
      "time": "2017-07-30 07:00:42.846621+00",
      "chamber_id": "1",
      "temperature": "77",
      "humidity": "50",
      "pH": null,
      "PPM": null,
      "height": null,
      "water": null,
      "photo": null
    },
    {
      "time": "2017-07-30 07:28:42.846621+00",
      "chamber_id": "1",
      "temperature": "77",
      "humidity": "50",
      "pH": null,
      "PPM": null,
      "height": null,
      "water": null,
      "photo": null
    },
    {
      "time": "2017-07-30 07:56:42.846621+00",
      "chamber_id": "1",
      "temperature": "77",
      "humidity": "50",
      "pH": null,
      "PPM": null,
      "height": null,
      "water": null,
      "photo": null
    },
    {
      "time": "2017-07-30 08:24:42.846621+00",
      "chamber_id": "1",
      "temperature": "77",
      "humidity": "50",
      "pH": null,
      "PPM": null,
      "height": null,
      "water": null,
      "photo": null
    },
    {
      "time": "2017-07-30 08:52:42.846621+00",
      "chamber_id": "1",
      "temperature": "77",
      "humidity": "50",
      "pH": null,
      "PPM": null,
      "height": null,
      "water": null,
      "photo": null
    },
    {
      "time": "2017-07-30 09:20:42.846621+00",
      "chamber_id": "1",
      "temperature": "77",
      "humidity": "50",
      "pH": null,
      "PPM": null,
      "height": null,
      "water": null,
      "photo": null
    },
    {
      "time": "2017-07-30 09:48:42.846621+00",
      "chamber_id": "1",
      "temperature": "77",
      "humidity": "50",
      "pH": null,
      "PPM": null,
      "height": null,
      "water": null,
      "photo": null
    },
    {
      "time": "2017-07-30 10:00:00.846621+00",
      "chamber_id": "1",
      "temperature": "77",
      "humidity": "50",
      "pH": "5.9",
      "PPM": "345",
      "height": "6",
      "water": "85",
      "photo": "na"
    },
    {
      "time": "2017-07-30 10:28:42.846621+00",
      "chamber_id": "1",
      "temperature": "77",
      "humidity": "50",
      "pH": null,
      "PPM": null,
      "height": null,
      "water": null,
      "photo": null
    },
    {
      "time": "2017-07-30 10:56:42.846621+00",
      "chamber_id": "1",
      "temperature": "77",
      "humidity": "50",
      "pH": null,
      "PPM": null,
      "height": null,
      "water": null,
      "photo": null
    },
    {
      "time": "2017-07-30 11:24:42.846621+00",
      "chamber_id": "1",
      "temperature": "77",
      "humidity": "50",
      "pH": null,
      "PPM": null,
      "height": null,
      "water": null,
      "photo": null
    },
    {
      "time": "2017-07-30 11:52:42.846621+00",
      "chamber_id": "1",
      "temperature": "78",
      "humidity": "50",
      "pH": null,
      "PPM": null,
      "height": null,
      "water": null,
      "photo": null
    },
    {
      "time": "2017-07-30 12:20:42.846621+00",
      "chamber_id": "1",
      "temperature": "77",
      "humidity": "50",
      "pH": null,
      "PPM": null,
      "height": null,
      "water": null,
      "photo": null
    },
    {
      "time": "2017-07-30 12:48:42.846621+00",
      "chamber_id": "1",
      "temperature": "77",
      "humidity": "50",
      "pH": null,
      "PPM": null,
      "height": null,
      "water": null,
      "photo": null
    },
    {
      "time": "2017-07-30 13:16:42.846621+00",
      "chamber_id": "1",
      "temperature": "77",
      "humidity": "50",
      "pH": null,
      "PPM": null,
      "height": null,
      "water": null,
      "photo": null
    },
    {
      "time": "2017-07-30 13:44:42.846621+00",
      "chamber_id": "1",
      "temperature": "77",
      "humidity": "50",
      "pH": null,
      "PPM": null,
      "height": null,
      "water": null,
      "photo": null
    },
    {
      "time": "2017-07-30 14:12:42.846621+00",
      "chamber_id": "1",
      "temperature": "77",
      "humidity": "50",
      "pH": null,
      "PPM": null,
      "height": null,
      "water": null,
      "photo": null
    },
    {
      "time": "2017-07-30 14:40:42.846621+00",
      "chamber_id": "1",
      "temperature": "77",
      "humidity": "50",
      "pH": null,
      "PPM": null,
      "height": null,
      "water": null,
      "photo": null
    },
    {
      "time": "2017-07-30 15:08:42.846621+00",
      "chamber_id": "1",
      "temperature": "77",
      "humidity": "50",
      "pH": null,
      "PPM": null,
      "height": null,
      "water": null,
      "photo": null
    },
    {
      "time": "2017-07-30 15:08:42.846621+00",
      "chamber_id": "1",
      "temperature": "77",
      "humidity": "50",
      "pH": null,
      "PPM": null,
      "height": null,
      "water": null,
      "photo": null
    },
    {
      "time": "2017-07-30 15:36:42.846621+00",
      "chamber_id": "1",
      "temperature": "77",
      "humidity": "50",
      "pH": null,
      "PPM": null,
      "height": null,
      "water": null,
      "photo": null
    },
    {
      "time": "2017-07-30 16:04:42.846621+00",
      "chamber_id": "1",
      "temperature": "77",
      "humidity": "50",
      "pH": "5.8",
      "PPM": null,
      "height": null,
      "water": null,
      "photo": "na"
    },
    {
      "time": "2017-07-30 16:32:42.846621+00",
      "chamber_id": "1",
      "temperature": "77",
      "humidity": "50",
      "pH": null,
      "PPM": null,
      "height": null,
      "water": null,
      "photo": null
    },
    {
      "time": "2017-07-30 17:00:42.846621+00",
      "chamber_id": "1",
      "temperature": "77",
      "humidity": "50",
      "pH": null,
      "PPM": null,
      "height": null,
      "water": null,
      "photo": null
    },
    {
      "time": "2017-07-30 17:28:42.846621+00",
      "chamber_id": "1",
      "temperature": "77",
      "humidity": "50",
      "pH": null,
      "PPM": null,
      "height": null,
      "water": null,
      "photo": null
    },
    {
      "time": "2017-07-30 17:56:42.846621+00",
      "chamber_id": "1",
      "temperature": "77",
      "humidity": "50",
      "pH": null,
      "PPM": null,
      "height": null,
      "water": null,
      "photo": null
    },
    {
      "time": "2017-07-30 18:24:42.846621+00",
      "chamber_id": "1",
      "temperature": "77",
      "humidity": "50",
      "pH": null,
      "PPM": null,
      "height": null,
      "water": null,
      "photo": null
    },
    {
      "time": "2017-07-30 18:52:42.846621+00",
      "chamber_id": "1",
      "temperature": "77",
      "humidity": "50",
      "pH": null,
      "PPM": null,
      "height": null,
      "water": null,
      "photo": null
    },
    {
      "time": "2017-07-30 19:20:42.846621+00",
      "chamber_id": "1",
      "temperature": "73",
      "humidity": "50",
      "pH": null,
      "PPM": null,
      "height": null,
      "water": null,
      "photo": null
    },
    {
      "time": "2017-07-30 19:48:42.846621+00",
      "chamber_id": "1",
      "temperature": "74",
      "humidity": "50",
      "pH": null,
      "PPM": null,
      "height": null,
      "water": null,
      "photo": null
    },
    {
      "time": "2017-07-30 20:16:42.846621+00",
      "chamber_id": "1",
      "temperature": "77",
      "humidity": "50",
      "pH": null,
      "PPM": null,
      "height": null,
      "water": null,
      "photo": null
    },
    {
      "time": "2017-07-30 20:44:42.846621+00",
      "chamber_id": "1",
      "temperature": "77",
      "humidity": "50",
      "pH": null,
      "PPM": null,
      "height": null,
      "water": null,
      "photo": null
    },
    {
      "time": "2017-07-30 21:12:42.846621+00",
      "chamber_id": "1",
      "temperature": "77",
      "humidity": "50",
      "pH": null,
      "PPM": null,
      "height": null,
      "water": null,
      "photo": null
    },
    {
      "time": "2017-07-30 21:40:42.846621+00",
      "chamber_id": "1",
      "temperature": "77",
      "humidity": "50",
      "pH": null,
      "PPM": null,
      "height": null,
      "water": null,
      "photo": null
    },
    {
      "time": "2017-07-30 22:08:42.846621+00",
      "chamber_id": "1",
      "temperature": "77",
      "humidity": "50",
      "pH": null,
      "PPM": null,
      "height": null,
      "water": null,
      "photo": null
    },
    {
      "time": "2017-07-30 22:36:42.846621+00",
      "chamber_id": "1",
      "temperature": "77",
      "humidity": "50",
      "pH": null,
      "PPM": null,
      "height": null,
      "water": null,
      "photo": null
    },
    {
      "time": "2017-07-30 23:04:42.846621+00",
      "chamber_id": "1",
      "temperature": "77",
      "humidity": "50",
      "pH": null,
      "PPM": null,
      "height": null,
      "water": null,
      "photo": null
    },
    {
      "time": "2017-07-30 23:32:42.846621+00",
      "chamber_id": "1",
      "temperature": "77",
      "humidity": "50",
      "pH": null,
      "PPM": null,
      "height": null,
      "water": null,
      "photo": null
    },
    {
      "time": "2017-07-31 00:00:42.846621+00",
      "chamber_id": "1",
      "temperature": "77",
      "humidity": "50",
      "pH": null,
      "PPM": null,
      "height": null,
      "water": null,
      "photo": null
    },
    {
      "time": "2017-07-31 00:28:42.846621+00",
      "chamber_id": "1",
      "temperature": "77",
      "humidity": "50",
      "pH": null,
      "PPM": null,
      "height": null,
      "water": null,
      "photo": null
    },
    {
      "time": "2017-07-31 00:56:42.846621+00",
      "chamber_id": "1",
      "temperature": "77",
      "humidity": "50",
      "pH": null,
      "PPM": null,
      "height": null,
      "water": null,
      "photo": null
    },
    {
      "time": "2017-07-31 01:24:42.846621+00",
      "chamber_id": "1",
      "temperature": "77",
      "humidity": "50",
      "pH": null,
      "PPM": null,
      "height": null,
      "water": null,
      "photo": null
    },
    {
      "time": "2017-07-31 01:52:42.846621+00",
      "chamber_id": "1",
      "temperature": "77",
      "humidity": "50",
      "pH": null,
      "PPM": null,
      "height": null,
      "water": null,
      "photo": null
    },
    {
      "time": "2017-07-31 02:20:42.846621+00",
      "chamber_id": "1",
      "temperature": "77",
      "humidity": "50",
      "pH": null,
      "PPM": null,
      "height": null,
      "water": null,
      "photo": null
    },
    {
      "time": "2017-07-31 02:48:42.846621+00",
      "chamber_id": "1",
      "temperature": "77",
      "humidity": "50",
      "pH": null,
      "PPM": null,
      "height": null,
      "water": null,
      "photo": null
    },
    {
      "time": "2017-07-31 03:16:42.846621+00",
      "chamber_id": "1",
      "temperature": "77",
      "humidity": "50",
      "pH": null,
      "PPM": null,
      "height": null,
      "water": null,
      "photo": null
    },
    {
      "time": "2017-07-31 03:16:42.846621+00",
      "chamber_id": "1",
      "temperature": "77",
      "humidity": "50",
      "pH": null,
      "PPM": null,
      "height": null,
      "water": null,
      "photo": null
    },
    {
      "time": "2017-07-31 03:44:42.846621+00",
      "chamber_id": "1",
      "temperature": "77",
      "humidity": "50",
      "pH": null,
      "PPM": null,
      "height": null,
      "water": null,
      "photo": null
    },
    {
      "time": "2017-07-31 04:12:42.846621+00",
      "chamber_id": "1",
      "temperature": "77",
      "humidity": "50",
      "pH": null,
      "PPM": null,
      "height": null,
      "water": null,
      "photo": null
    },
    {
      "time": "2017-07-31 04:40:42.846621+00",
      "chamber_id": "1",
      "temperature": "77",
      "humidity": "50",
      "pH": null,
      "PPM": null,
      "height": null,
      "water": null,
      "photo": null
    },
    {
      "time": "2017-07-31 05:08:42.846621+00",
      "chamber_id": "1",
      "temperature": "77",
      "humidity": "50",
      "pH": null,
      "PPM": null,
      "height": null,
      "water": null,
      "photo": null
    },
    {
      "time": "2017-07-31 05:36:42.846621+00",
      "chamber_id": "1",
      "temperature": "77",
      "humidity": "50",
      "pH": null,
      "PPM": null,
      "height": null,
      "water": null,
      "photo": null
    },
    {
      "time": "2017-07-31 06:04:42.846621+00",
      "chamber_id": "1",
      "temperature": "77",
      "humidity": "50",
      "pH": null,
      "PPM": null,
      "height": null,
      "water": null,
      "photo": null
    },
    {
      "time": "2017-07-31 06:32:42.846621+00",
      "chamber_id": "1",
      "temperature": "77",
      "humidity": "50",
      "pH": null,
      "PPM": null,
      "height": null,
      "water": null,
      "photo": null
    },
    {
      "time": "2017-07-31 07:00:42.846621+00",
      "chamber_id": "1",
      "temperature": "77",
      "humidity": "50",
      "pH": null,
      "PPM": null,
      "height": null,
      "water": null,
      "photo": null
    },
    {
      "time": "2017-07-31 07:28:42.846621+00",
      "chamber_id": "1",
      "temperature": "77",
      "humidity": "50",
      "pH": null,
      "PPM": null,
      "height": null,
      "water": null,
      "photo": null
    },
    {
      "time": "2017-07-31 07:56:42.846621+00",
      "chamber_id": "1",
      "temperature": "77",
      "humidity": "50",
      "pH": null,
      "PPM": null,
      "height": null,
      "water": null,
      "photo": null
    },
    {
      "time": "2017-07-31 08:24:42.846621+00",
      "chamber_id": "1",
      "temperature": "77",
      "humidity": "50",
      "pH": null,
      "PPM": null,
      "height": null,
      "water": null,
      "photo": null
    },
    {
      "time": "2017-07-31 08:52:42.846621+00",
      "chamber_id": "1",
      "temperature": "77",
      "humidity": "50",
      "pH": null,
      "PPM": null,
      "height": null,
      "water": null,
      "photo": null
    },
    {
      "time": "2017-07-31 09:20:42.846621+00",
      "chamber_id": "1",
      "temperature": "77",
      "humidity": "50",
      "pH": null,
      "PPM": null,
      "height": null,
      "water": null,
      "photo": null
    },
    {
      "time": "2017-07-31 09:48:42.846621+00",
      "chamber_id": "1",
      "temperature": "77",
      "humidity": "50",
      "pH": null,
      "PPM": null,
      "height": null,
      "water": null,
      "photo": null
    },
    {
      "time": "2017-07-31 10:00:00.846621+00",
      "chamber_id": "1",
      "temperature": "74",
      "humidity": "50",
      "pH": "5.9",
      "PPM": "350",
      "height": "6.5",
      "water": "80",
      "photo": "na"
    },
    {
      "time": "2017-07-31 10:28:42.846621+00",
      "chamber_id": "1",
      "temperature": "75",
      "humidity": "50",
      "pH": null,
      "PPM": null,
      "height": null,
      "water": null,
      "photo": null
    },
    {
      "time": "2017-07-31 10:56:42.846621+00",
      "chamber_id": "1",
      "temperature": "75",
      "humidity": "50",
      "pH": null,
      "PPM": null,
      "height": null,
      "water": null,
      "photo": null
    },
    {
      "time": "2017-07-31 11:24:42.846621+00",
      "chamber_id": "1",
      "temperature": "75",
      "humidity": "50",
      "pH": null,
      "PPM": null,
      "height": null,
      "water": null,
      "photo": null
    },
    {
      "time": "2017-07-31 11:52:42.846621+00",
      "chamber_id": "1",
      "temperature": "78",
      "humidity": "50",
      "pH": null,
      "PPM": null,
      "height": null,
      "water": null,
      "photo": null
    },
    {
      "time": "2017-07-31 12:20:42.846621+00",
      "chamber_id": "1",
      "temperature": "77",
      "humidity": "50",
      "pH": null,
      "PPM": null,
      "height": null,
      "water": null,
      "photo": null
    },
    {
      "time": "2017-07-31 12:48:42.846621+00",
      "chamber_id": "1",
      "temperature": "77",
      "humidity": "50",
      "pH": null,
      "PPM": null,
      "height": null,
      "water": null,
      "photo": null
    },
    {
      "time": "2017-07-31 13:16:42.846621+00",
      "chamber_id": "1",
      "temperature": "77",
      "humidity": "50",
      "pH": null,
      "PPM": null,
      "height": null,
      "water": null,
      "photo": null
    },
    {
      "time": "2017-07-31 13:44:42.846621+00",
      "chamber_id": "1",
      "temperature": "77",
      "humidity": "50",
      "pH": null,
      "PPM": null,
      "height": null,
      "water": null,
      "photo": null
    },
    {
      "time": "2017-07-31 14:12:42.846621+00",
      "chamber_id": "1",
      "temperature": "77",
      "humidity": "50",
      "pH": null,
      "PPM": null,
      "height": null,
      "water": null,
      "photo": null
    },
    {
      "time": "2017-07-31 14:40:42.846621+00",
      "chamber_id": "1",
      "temperature": "77",
      "humidity": "50",
      "pH": null,
      "PPM": null,
      "height": null,
      "water": null,
      "photo": null
    },
    {
      "time": "2017-07-31 15:08:42.846621+00",
      "chamber_id": "1",
      "temperature": "77",
      "humidity": "50",
      "pH": null,
      "PPM": null,
      "height": null,
      "water": null,
      "photo": null
    },
    {
      "time": "2017-07-31 15:08:42.846621+00",
      "chamber_id": "1",
      "temperature": "77",
      "humidity": "50",
      "pH": null,
      "PPM": null,
      "height": null,
      "water": null,
      "photo": null
    },
    {
      "time": "2017-07-31 15:36:42.846621+00",
      "chamber_id": "1",
      "temperature": "77",
      "humidity": "50",
      "pH": null,
      "PPM": null,
      "height": null,
      "water": null,
      "photo": null
    },
    {
      "time": "2017-07-31 16:04:42.846621+00",
      "chamber_id": "1",
      "temperature": "77",
      "humidity": "50",
      "pH": "5.8",
      "PPM": null,
      "height": null,
      "water": null,
      "photo": "na"
    },
    {
      "time": "2017-07-31 16:32:42.846621+00",
      "chamber_id": "1",
      "temperature": "77",
      "humidity": "50",
      "pH": null,
      "PPM": null,
      "height": null,
      "water": null,
      "photo": null
    },
    {
      "time": "2017-07-31 17:00:42.846621+00",
      "chamber_id": "1",
      "temperature": "77",
      "humidity": "50",
      "pH": null,
      "PPM": null,
      "height": null,
      "water": null,
      "photo": null
    },
    {
      "time": "2017-07-31 17:28:42.846621+00",
      "chamber_id": "1",
      "temperature": "77",
      "humidity": "50",
      "pH": null,
      "PPM": null,
      "height": null,
      "water": null,
      "photo": null
    },
    {
      "time": "2017-07-31 17:56:42.846621+00",
      "chamber_id": "1",
      "temperature": "77",
      "humidity": "50",
      "pH": null,
      "PPM": null,
      "height": null,
      "water": null,
      "photo": null
    },
    {
      "time": "2017-07-31 18:24:42.846621+00",
      "chamber_id": "1",
      "temperature": "77",
      "humidity": "50",
      "pH": null,
      "PPM": null,
      "height": null,
      "water": null,
      "photo": null
    },
    {
      "time": "2017-07-31 18:52:42.846621+00",
      "chamber_id": "1",
      "temperature": "77",
      "humidity": "50",
      "pH": null,
      "PPM": null,
      "height": null,
      "water": null,
      "photo": null
    },
    {
      "time": "2017-07-31 19:20:42.846621+00",
      "chamber_id": "1",
      "temperature": "73",
      "humidity": "50",
      "pH": null,
      "PPM": null,
      "height": null,
      "water": null,
      "photo": null
    },
    {
      "time": "2017-07-31 19:48:42.846621+00",
      "chamber_id": "1",
      "temperature": "74",
      "humidity": "50",
      "pH": null,
      "PPM": null,
      "height": null,
      "water": null,
      "photo": null
    },
    {
      "time": "2017-07-31 20:16:42.846621+00",
      "chamber_id": "1",
      "temperature": "77",
      "humidity": "50",
      "pH": null,
      "PPM": null,
      "height": null,
      "water": null,
      "photo": null
    },
    {
      "time": "2017-07-31 20:44:42.846621+00",
      "chamber_id": "1",
      "temperature": "77",
      "humidity": "50",
      "pH": null,
      "PPM": null,
      "height": null,
      "water": null,
      "photo": null
    },
    {
      "time": "2017-07-31 21:12:42.846621+00",
      "chamber_id": "1",
      "temperature": "77",
      "humidity": "50",
      "pH": null,
      "PPM": null,
      "height": null,
      "water": null,
      "photo": null
    },
    {
      "time": "2017-07-31 21:40:42.846621+00",
      "chamber_id": "1",
      "temperature": "77",
      "humidity": "50",
      "pH": null,
      "PPM": null,
      "height": null,
      "water": null,
      "photo": null
    },
    {
      "time": "2017-07-31 22:08:42.846621+00",
      "chamber_id": "1",
      "temperature": "77",
      "humidity": "50",
      "pH": null,
      "PPM": null,
      "height": null,
      "water": null,
      "photo": null
    },
    {
      "time": "2017-07-31 22:36:42.846621+00",
      "chamber_id": "1",
      "temperature": "77",
      "humidity": "50",
      "pH": null,
      "PPM": null,
      "height": null,
      "water": null,
      "photo": null
    },
    {
      "time": "2017-07-31 23:04:42.846621+00",
      "chamber_id": "1",
      "temperature": "77",
      "humidity": "50",
      "pH": null,
      "PPM": null,
      "height": null,
      "water": null,
      "photo": null
    },
    {
      "time": "2017-07-31 23:32:42.846621+00",
      "chamber_id": "1",
      "temperature": "77",
      "humidity": "50",
      "pH": null,
      "PPM": null,
      "height": null,
      "water": null,
      "photo": null
    },
    {
      "time": "2017-08-01 00:00:42.846621+00",
      "chamber_id": "1",
      "temperature": "77",
      "humidity": "50",
      "pH": null,
      "PPM": null,
      "height": null,
      "water": null,
      "photo": null
    },
    {
      "time": "2017-08-01 00:28:42.846621+00",
      "chamber_id": "1",
      "temperature": "77",
      "humidity": "50",
      "pH": null,
      "PPM": null,
      "height": null,
      "water": null,
      "photo": null
    },
    {
      "time": "2017-08-01 00:56:42.846621+00",
      "chamber_id": "1",
      "temperature": "77",
      "humidity": "50",
      "pH": null,
      "PPM": null,
      "height": null,
      "water": null,
      "photo": null
    },
    {
      "time": "2017-08-01 01:24:42.846621+00",
      "chamber_id": "1",
      "temperature": "77",
      "humidity": "50",
      "pH": null,
      "PPM": null,
      "height": null,
      "water": null,
      "photo": null
    },
    {
      "time": "2017-08-01 01:52:42.846621+00",
      "chamber_id": "1",
      "temperature": "77",
      "humidity": "50",
      "pH": null,
      "PPM": null,
      "height": null,
      "water": null,
      "photo": null
    },
    {
      "time": "2017-08-01 02:20:42.846621+00",
      "chamber_id": "1",
      "temperature": "77",
      "humidity": "50",
      "pH": null,
      "PPM": null,
      "height": null,
      "water": null,
      "photo": null
    },
    {
      "time": "2017-08-01 02:48:42.846621+00",
      "chamber_id": "1",
      "temperature": "77",
      "humidity": "50",
      "pH": null,
      "PPM": null,
      "height": null,
      "water": null,
      "photo": null
    },
    {
      "time": "2017-08-01 03:16:42.846621+00",
      "chamber_id": "1",
      "temperature": "77",
      "humidity": "50",
      "pH": null,
      "PPM": null,
      "height": null,
      "water": null,
      "photo": null
    },
    {
      "time": "2017-08-01 03:16:42.846621+00",
      "chamber_id": "1",
      "temperature": "77",
      "humidity": "50",
      "pH": null,
      "PPM": null,
      "height": null,
      "water": null,
      "photo": null
    },
    {
      "time": "2017-08-01 03:44:42.846621+00",
      "chamber_id": "1",
      "temperature": "77",
      "humidity": "50",
      "pH": null,
      "PPM": null,
      "height": null,
      "water": null,
      "photo": null
    },
    {
      "time": "2017-08-01 04:12:42.846621+00",
      "chamber_id": "1",
      "temperature": "77",
      "humidity": "50",
      "pH": null,
      "PPM": null,
      "height": null,
      "water": null,
      "photo": null
    },
    {
      "time": "2017-08-01 04:40:42.846621+00",
      "chamber_id": "1",
      "temperature": "77",
      "humidity": "50",
      "pH": null,
      "PPM": null,
      "height": null,
      "water": null,
      "photo": null
    },
    {
      "time": "2017-08-01 05:08:42.846621+00",
      "chamber_id": "1",
      "temperature": "77",
      "humidity": "50",
      "pH": null,
      "PPM": null,
      "height": null,
      "water": null,
      "photo": null
    },
    {
      "time": "2017-08-01 05:36:42.846621+00",
      "chamber_id": "1",
      "temperature": "77",
      "humidity": "50",
      "pH": null,
      "PPM": null,
      "height": null,
      "water": null,
      "photo": null
    },
    {
      "time": "2017-08-01 06:04:42.846621+00",
      "chamber_id": "1",
      "temperature": "77",
      "humidity": "50",
      "pH": null,
      "PPM": null,
      "height": null,
      "water": null,
      "photo": null
    },
    {
      "time": "2017-08-01 06:32:42.846621+00",
      "chamber_id": "1",
      "temperature": "77",
      "humidity": "50",
      "pH": null,
      "PPM": null,
      "height": null,
      "water": null,
      "photo": null
    },
    {
      "time": "2017-08-01 07:00:42.846621+00",
      "chamber_id": "1",
      "temperature": "77",
      "humidity": "50",
      "pH": null,
      "PPM": null,
      "height": null,
      "water": null,
      "photo": null
    },
    {
      "time": "2017-08-01 07:28:42.846621+00",
      "chamber_id": "1",
      "temperature": "77",
      "humidity": "50",
      "pH": null,
      "PPM": null,
      "height": null,
      "water": null,
      "photo": null
    },
    {
      "time": "2017-08-01 07:56:42.846621+00",
      "chamber_id": "1",
      "temperature": "77",
      "humidity": "50",
      "pH": null,
      "PPM": null,
      "height": null,
      "water": null,
      "photo": null
    },
    {
      "time": "2017-08-01 08:24:42.846621+00",
      "chamber_id": "1",
      "temperature": "77",
      "humidity": "50",
      "pH": null,
      "PPM": null,
      "height": null,
      "water": null,
      "photo": null
    },
    {
      "time": "2017-08-01 08:52:42.846621+00",
      "chamber_id": "1",
      "temperature": "77",
      "humidity": "50",
      "pH": null,
      "PPM": null,
      "height": null,
      "water": null,
      "photo": null
    },
    {
      "time": "2017-08-01 09:20:42.846621+00",
      "chamber_id": "1",
      "temperature": "77",
      "humidity": "50",
      "pH": null,
      "PPM": null,
      "height": null,
      "water": null,
      "photo": null
    },
    {
      "time": "2017-08-01 09:48:42.846621+00",
      "chamber_id": "1",
      "temperature": "77",
      "humidity": "50",
      "pH": null,
      "PPM": null,
      "height": null,
      "water": null,
      "photo": null
    },
    {
      "time": "2017-08-01 10:00:00.846621+00",
      "chamber_id": "1",
      "temperature": "74",
      "humidity": "50",
      "pH": "5.9",
      "PPM": "350",
      "height": null,
      "water": null,
      "photo": "na"
    },
    {
      "time": "2017-08-01 10:28:42.846621+00",
      "chamber_id": "1",
      "temperature": "75",
      "humidity": "50",
      "pH": null,
      "PPM": null,
      "height": null,
      "water": null,
      "photo": null
    },
    {
      "time": "2017-08-01 10:56:42.846621+00",
      "chamber_id": "1",
      "temperature": "75",
      "humidity": "50",
      "pH": null,
      "PPM": null,
      "height": null,
      "water": null,
      "photo": null
    },
    {
      "time": "2017-08-01 11:24:42.846621+00",
      "chamber_id": "1",
      "temperature": "75",
      "humidity": "50",
      "pH": null,
      "PPM": null,
      "height": null,
      "water": null,
      "photo": null
    },
    {
      "time": "2017-08-01 11:52:42.846621+00",
      "chamber_id": "1",
      "temperature": "78",
      "humidity": "50",
      "pH": null,
      "PPM": null,
      "height": null,
      "water": null,
      "photo": null
    },
    {
      "time": "2017-08-01 12:20:42.846621+00",
      "chamber_id": "1",
      "temperature": "77",
      "humidity": "50",
      "pH": null,
      "PPM": null,
      "height": null,
      "water": null,
      "photo": null
    },
    {
      "time": "2017-08-01 12:48:42.846621+00",
      "chamber_id": "1",
      "temperature": "77",
      "humidity": "50",
      "pH": null,
      "PPM": null,
      "height": null,
      "water": null,
      "photo": null
    },
    {
      "time": "2017-08-01 13:16:42.846621+00",
      "chamber_id": "1",
      "temperature": "77",
      "humidity": "50",
      "pH": null,
      "PPM": null,
      "height": null,
      "water": null,
      "photo": null
    },
    {
      "time": "2017-08-01 13:44:42.846621+00",
      "chamber_id": "1",
      "temperature": "77",
      "humidity": "50",
      "pH": null,
      "PPM": null,
      "height": null,
      "water": null,
      "photo": null
    },
    {
      "time": "2017-08-01 14:12:42.846621+00",
      "chamber_id": "1",
      "temperature": "77",
      "humidity": "50",
      "pH": null,
      "PPM": null,
      "height": null,
      "water": null,
      "photo": null
    },
    {
      "time": "2017-08-01 14:40:42.846621+00",
      "chamber_id": "1",
      "temperature": "77",
      "humidity": "50",
      "pH": null,
      "PPM": null,
      "height": null,
      "water": null,
      "photo": null
    },
    {
      "time": "2017-08-01 15:08:42.846621+00",
      "chamber_id": "1",
      "temperature": "77",
      "humidity": "50",
      "pH": null,
      "PPM": null,
      "height": null,
      "water": null,
      "photo": null
    },
    {
      "time": "2017-08-01 15:08:42.846621+00",
      "chamber_id": "1",
      "temperature": "77",
      "humidity": "50",
      "pH": null,
      "PPM": null,
      "height": null,
      "water": null,
      "photo": null
    },
    {
      "time": "2017-08-01 15:36:42.846621+00",
      "chamber_id": "1",
      "temperature": "77",
      "humidity": "50",
      "pH": null,
      "PPM": null,
      "height": null,
      "water": null,
      "photo": null
    },
    {
      "time": "2017-08-01 16:04:42.846621+00",
      "chamber_id": "1",
      "temperature": "77",
      "humidity": "50",
      "pH": "5.8",
      "PPM": null,
      "height": null,
      "water": null,
      "photo": "na"
    },
    {
      "time": "2017-08-01 16:32:42.846621+00",
      "chamber_id": "1",
      "temperature": "77",
      "humidity": "50",
      "pH": null,
      "PPM": null,
      "height": null,
      "water": null,
      "photo": null
    },
    {
      "time": "2017-08-01 17:00:42.846621+00",
      "chamber_id": "1",
      "temperature": "77",
      "humidity": "50",
      "pH": null,
      "PPM": null,
      "height": null,
      "water": null,
      "photo": null
    },
    {
      "time": "2017-08-01 17:28:42.846621+00",
      "chamber_id": "1",
      "temperature": "77",
      "humidity": "50",
      "pH": null,
      "PPM": null,
      "height": null,
      "water": null,
      "photo": null
    },
    {
      "time": "2017-08-01 17:56:42.846621+00",
      "chamber_id": "1",
      "temperature": "77",
      "humidity": "50",
      "pH": null,
      "PPM": null,
      "height": null,
      "water": null,
      "photo": null
    },
    {
      "time": "2017-08-01 18:24:42.846621+00",
      "chamber_id": "1",
      "temperature": "77",
      "humidity": "50",
      "pH": null,
      "PPM": null,
      "height": null,
      "water": null,
      "photo": null
    },
    {
      "time": "2017-08-01 18:52:42.846621+00",
      "chamber_id": "1",
      "temperature": "77",
      "humidity": "50",
      "pH": null,
      "PPM": null,
      "height": null,
      "water": null,
      "photo": null
    },
    {
      "time": "2017-08-01 19:20:42.846621+00",
      "chamber_id": "1",
      "temperature": "73",
      "humidity": "50",
      "pH": null,
      "PPM": null,
      "height": null,
      "water": null,
      "photo": null
    },
    {
      "time": "2017-08-01 19:48:42.846621+00",
      "chamber_id": "1",
      "temperature": "74",
      "humidity": "50",
      "pH": null,
      "PPM": null,
      "height": null,
      "water": null,
      "photo": null
    },
    {
      "time": "2017-08-01 20:16:42.846621+00",
      "chamber_id": "1",
      "temperature": "77",
      "humidity": "50",
      "pH": null,
      "PPM": null,
      "height": null,
      "water": null,
      "photo": null
    },
    {
      "time": "2017-08-01 20:44:42.846621+00",
      "chamber_id": "1",
      "temperature": "77",
      "humidity": "50",
      "pH": null,
      "PPM": null,
      "height": null,
      "water": null,
      "photo": null
    },
    {
      "time": "2017-08-01 21:12:42.846621+00",
      "chamber_id": "1",
      "temperature": "77",
      "humidity": "50",
      "pH": null,
      "PPM": null,
      "height": null,
      "water": null,
      "photo": null
    },
    {
      "time": "2017-08-01 21:40:42.846621+00",
      "chamber_id": "1",
      "temperature": "77",
      "humidity": "50",
      "pH": null,
      "PPM": null,
      "height": null,
      "water": null,
      "photo": null
    },
    {
      "time": "2017-08-01 22:08:42.846621+00",
      "chamber_id": "1",
      "temperature": "77",
      "humidity": "50",
      "pH": null,
      "PPM": null,
      "height": null,
      "water": null,
      "photo": null
    },
    {
      "time": "2017-08-01 22:36:42.846621+00",
      "chamber_id": "1",
      "temperature": "77",
      "humidity": "50",
      "pH": null,
      "PPM": null,
      "height": null,
      "water": null,
      "photo": null
    },
    {
      "time": "2017-08-01 23:04:42.846621+00",
      "chamber_id": "1",
      "temperature": "77",
      "humidity": "50",
      "pH": null,
      "PPM": null,
      "height": null,
      "water": null,
      "photo": null
    },
    {
      "time": "2017-08-01 23:32:42.846621+00",
      "chamber_id": "1",
      "temperature": "77",
      "humidity": "50",
      "pH": null,
      "PPM": null,
      "height": null,
      "water": null,
      "photo": null
    },
    {
      "time": "2017-08-02 00:00:42.846621+00",
      "chamber_id": "1",
      "temperature": "77",
      "humidity": "50",
      "pH": null,
      "PPM": null,
      "height": null,
      "water": null,
      "photo": null
    },
    {
      "time": "2017-08-02 00:28:42.846621+00",
      "chamber_id": "1",
      "temperature": "77",
      "humidity": "50",
      "pH": null,
      "PPM": null,
      "height": null,
      "water": null,
      "photo": null
    },
    {
      "time": "2017-08-02 00:56:42.846621+00",
      "chamber_id": "1",
      "temperature": "77",
      "humidity": "50",
      "pH": null,
      "PPM": null,
      "height": null,
      "water": null,
      "photo": null
    },
    {
      "time": "2017-08-02 01:24:42.846621+00",
      "chamber_id": "1",
      "temperature": "77",
      "humidity": "50",
      "pH": null,
      "PPM": null,
      "height": null,
      "water": null,
      "photo": null
    },
    {
      "time": "2017-08-02 01:52:42.846621+00",
      "chamber_id": "1",
      "temperature": "77",
      "humidity": "50",
      "pH": null,
      "PPM": null,
      "height": null,
      "water": null,
      "photo": null
    },
    {
      "time": "2017-08-02 02:20:42.846621+00",
      "chamber_id": "1",
      "temperature": "77",
      "humidity": "50",
      "pH": null,
      "PPM": null,
      "height": null,
      "water": null,
      "photo": null
    },
    {
      "time": "2017-08-02 02:48:42.846621+00",
      "chamber_id": "1",
      "temperature": "77",
      "humidity": "50",
      "pH": null,
      "PPM": null,
      "height": null,
      "water": null,
      "photo": null
    },
    {
      "time": "2017-08-02 03:16:42.846621+00",
      "chamber_id": "1",
      "temperature": "77",
      "humidity": "50",
      "pH": null,
      "PPM": null,
      "height": null,
      "water": null,
      "photo": null
    },
    {
      "time": "2017-08-02 03:16:42.846621+00",
      "chamber_id": "1",
      "temperature": "77",
      "humidity": "50",
      "pH": null,
      "PPM": null,
      "height": null,
      "water": null,
      "photo": null
    },
    {
      "time": "2017-08-02 03:44:42.846621+00",
      "chamber_id": "1",
      "temperature": "77",
      "humidity": "50",
      "pH": null,
      "PPM": null,
      "height": null,
      "water": null,
      "photo": null
    },
    {
      "time": "2017-08-02 04:12:42.846621+00",
      "chamber_id": "1",
      "temperature": "77",
      "humidity": "50",
      "pH": null,
      "PPM": null,
      "height": null,
      "water": null,
      "photo": null
    },
    {
      "time": "2017-08-02 04:40:42.846621+00",
      "chamber_id": "1",
      "temperature": "77",
      "humidity": "50",
      "pH": null,
      "PPM": null,
      "height": null,
      "water": null,
      "photo": null
    },
    {
      "time": "2017-08-02 05:08:42.846621+00",
      "chamber_id": "1",
      "temperature": "77",
      "humidity": "50",
      "pH": null,
      "PPM": null,
      "height": null,
      "water": null,
      "photo": null
    },
    {
      "time": "2017-08-02 05:36:42.846621+00",
      "chamber_id": "1",
      "temperature": "77",
      "humidity": "50",
      "pH": null,
      "PPM": null,
      "height": null,
      "water": null,
      "photo": null
    },
    {
      "time": "2017-08-02 06:04:42.846621+00",
      "chamber_id": "1",
      "temperature": "77",
      "humidity": "50",
      "pH": null,
      "PPM": null,
      "height": null,
      "water": null,
      "photo": null
    },
    {
      "time": "2017-08-02 06:32:42.846621+00",
      "chamber_id": "1",
      "temperature": "77",
      "humidity": "50",
      "pH": null,
      "PPM": null,
      "height": null,
      "water": null,
      "photo": null
    },
    {
      "time": "2017-08-02 07:00:42.846621+00",
      "chamber_id": "1",
      "temperature": "77",
      "humidity": "50",
      "pH": null,
      "PPM": null,
      "height": null,
      "water": null,
      "photo": null
    },
    {
      "time": "2017-08-02 07:28:42.846621+00",
      "chamber_id": "1",
      "temperature": "77",
      "humidity": "50",
      "pH": null,
      "PPM": null,
      "height": null,
      "water": null,
      "photo": null
    },
    {
      "time": "2017-08-02 07:56:42.846621+00",
      "chamber_id": "1",
      "temperature": "77",
      "humidity": "50",
      "pH": null,
      "PPM": null,
      "height": null,
      "water": null,
      "photo": null
    },
    {
      "time": "2017-08-02 08:24:42.846621+00",
      "chamber_id": "1",
      "temperature": "77",
      "humidity": "50",
      "pH": null,
      "PPM": null,
      "height": null,
      "water": null,
      "photo": null
    },
    {
      "time": "2017-08-02 08:52:42.846621+00",
      "chamber_id": "1",
      "temperature": "77",
      "humidity": "50",
      "pH": null,
      "PPM": null,
      "height": null,
      "water": null,
      "photo": null
    },
    {
      "time": "2017-08-02 09:20:42.846621+00",
      "chamber_id": "1",
      "temperature": "77",
      "humidity": "50",
      "pH": null,
      "PPM": null,
      "height": null,
      "water": null,
      "photo": null
    },
    {
      "time": "2017-08-02 09:48:42.846621+00",
      "chamber_id": "1",
      "temperature": "77",
      "humidity": "50",
      "pH": null,
      "PPM": null,
      "height": null,
      "water": null,
      "photo": null
    },
    {
      "time": "2017-08-02 10:00:00.846621+00",
      "chamber_id": "1",
      "temperature": "74",
      "humidity": "50",
      "pH": "5.9",
      "PPM": "350",
      "height": null,
      "water": null,
      "photo": "na"
    },
    {
      "time": "2017-08-02 10:28:42.846621+00",
      "chamber_id": "1",
      "temperature": "75",
      "humidity": "50",
      "pH": null,
      "PPM": null,
      "height": null,
      "water": null,
      "photo": null
    },
    {
      "time": "2017-08-02 10:56:42.846621+00",
      "chamber_id": "1",
      "temperature": "75",
      "humidity": "50",
      "pH": null,
      "PPM": null,
      "height": null,
      "water": null,
      "photo": null
    },
    {
      "time": "2017-08-02 11:24:42.846621+00",
      "chamber_id": "1",
      "temperature": "75",
      "humidity": "50",
      "pH": null,
      "PPM": null,
      "height": null,
      "water": null,
      "photo": null
    },
    {
      "time": "2017-08-02 11:52:42.846621+00",
      "chamber_id": "1",
      "temperature": "78",
      "humidity": "50",
      "pH": null,
      "PPM": null,
      "height": null,
      "water": null,
      "photo": null
    },
    {
      "time": "2017-08-02 12:20:42.846621+00",
      "chamber_id": "1",
      "temperature": "77",
      "humidity": "50",
      "pH": null,
      "PPM": null,
      "height": null,
      "water": null,
      "photo": null
    },
    {
      "time": "2017-08-02 12:48:42.846621+00",
      "chamber_id": "1",
      "temperature": "77",
      "humidity": "50",
      "pH": null,
      "PPM": null,
      "height": null,
      "water": null,
      "photo": null
    },
    {
      "time": "2017-08-02 13:16:42.846621+00",
      "chamber_id": "1",
      "temperature": "77",
      "humidity": "50",
      "pH": null,
      "PPM": null,
      "height": null,
      "water": null,
      "photo": null
    },
    {
      "time": "2017-08-02 13:44:42.846621+00",
      "chamber_id": "1",
      "temperature": "77",
      "humidity": "50",
      "pH": null,
      "PPM": null,
      "height": null,
      "water": null,
      "photo": null
    },
    {
      "time": "2017-08-02 14:12:42.846621+00",
      "chamber_id": "1",
      "temperature": "77",
      "humidity": "50",
      "pH": null,
      "PPM": null,
      "height": null,
      "water": null,
      "photo": null
    },
    {
      "time": "2017-08-02 14:40:42.846621+00",
      "chamber_id": "1",
      "temperature": "77",
      "humidity": "50",
      "pH": null,
      "PPM": null,
      "height": null,
      "water": null,
      "photo": null
    },
    {
      "time": "2017-08-02 15:08:42.846621+00",
      "chamber_id": "1",
      "temperature": "77",
      "humidity": "50",
      "pH": null,
      "PPM": null,
      "height": null,
      "water": null,
      "photo": null
    },
    {
      "time": "2017-08-02 15:08:42.846621+00",
      "chamber_id": "1",
      "temperature": "77",
      "humidity": "50",
      "pH": null,
      "PPM": null,
      "height": null,
      "water": null,
      "photo": null
    },
    {
      "time": "2017-08-02 15:36:42.846621+00",
      "chamber_id": "1",
      "temperature": "77",
      "humidity": "50",
      "pH": null,
      "PPM": null,
      "height": null,
      "water": null,
      "photo": null
    },
    {
      "time": "2017-08-02 16:04:42.846621+00",
      "chamber_id": "1",
      "temperature": "77",
      "humidity": "50",
      "pH": "5.8",
      "PPM": null,
      "height": null,
      "water": null,
      "photo": "na"
    },
    {
      "time": "2017-08-02 16:32:42.846621+00",
      "chamber_id": "1",
      "temperature": "77",
      "humidity": "50",
      "pH": null,
      "PPM": null,
      "height": null,
      "water": null,
      "photo": null
    },
    {
      "time": "2017-08-02 17:00:42.846621+00",
      "chamber_id": "1",
      "temperature": "77",
      "humidity": "50",
      "pH": null,
      "PPM": null,
      "height": null,
      "water": null,
      "photo": null
    },
    {
      "time": "2017-08-02 17:28:42.846621+00",
      "chamber_id": "1",
      "temperature": "77",
      "humidity": "50",
      "pH": null,
      "PPM": null,
      "height": null,
      "water": null,
      "photo": null
    },
    {
      "time": "2017-08-02 17:56:42.846621+00",
      "chamber_id": "1",
      "temperature": "77",
      "humidity": "50",
      "pH": null,
      "PPM": null,
      "height": null,
      "water": null,
      "photo": null
    },
    {
      "time": "2017-08-02 18:24:42.846621+00",
      "chamber_id": "1",
      "temperature": "77",
      "humidity": "50",
      "pH": null,
      "PPM": null,
      "height": null,
      "water": null,
      "photo": null
    },
    {
      "time": "2017-08-02 18:52:42.846621+00",
      "chamber_id": "1",
      "temperature": "77",
      "humidity": "50",
      "pH": null,
      "PPM": null,
      "height": null,
      "water": null,
      "photo": null
    },
    {
      "time": "2017-08-02 19:20:42.846621+00",
      "chamber_id": "1",
      "temperature": "73",
      "humidity": "50",
      "pH": null,
      "PPM": null,
      "height": null,
      "water": null,
      "photo": null
    },
    {
      "time": "2017-08-02 19:48:42.846621+00",
      "chamber_id": "1",
      "temperature": "74",
      "humidity": "50",
      "pH": null,
      "PPM": null,
      "height": null,
      "water": null,
      "photo": null
    },
    {
      "time": "2017-08-02 20:16:42.846621+00",
      "chamber_id": "1",
      "temperature": "77",
      "humidity": "50",
      "pH": null,
      "PPM": null,
      "height": null,
      "water": null,
      "photo": null
    },
    {
      "time": "2017-08-02 20:44:42.846621+00",
      "chamber_id": "1",
      "temperature": "77",
      "humidity": "50",
      "pH": null,
      "PPM": null,
      "height": null,
      "water": null,
      "photo": null
    },
    {
      "time": "2017-08-02 21:12:42.846621+00",
      "chamber_id": "1",
      "temperature": "77",
      "humidity": "50",
      "pH": null,
      "PPM": null,
      "height": null,
      "water": null,
      "photo": null
    },
    {
      "time": "2017-08-02 21:40:42.846621+00",
      "chamber_id": "1",
      "temperature": "77",
      "humidity": "50",
      "pH": null,
      "PPM": null,
      "height": null,
      "water": null,
      "photo": null
    },
    {
      "time": "2017-08-02 22:08:42.846621+00",
      "chamber_id": "1",
      "temperature": "77",
      "humidity": "50",
      "pH": null,
      "PPM": null,
      "height": null,
      "water": null,
      "photo": null
    },
    {
      "time": "2017-08-02 22:36:42.846621+00",
      "chamber_id": "1",
      "temperature": "77",
      "humidity": "50",
      "pH": null,
      "PPM": null,
      "height": null,
      "water": null,
      "photo": null
    },
    {
      "time": "2017-08-02 23:04:42.846621+00",
      "chamber_id": "1",
      "temperature": "77",
      "humidity": "50",
      "pH": null,
      "PPM": null,
      "height": null,
      "water": null,
      "photo": null
    },
    {
      "time": "2017-08-02 23:32:42.846621+00",
      "chamber_id": "1",
      "temperature": "77",
      "humidity": "50",
      "pH": null,
      "PPM": null,
      "height": null,
      "water": null,
      "photo": null
    },
    {
      "time": "2017-08-03 00:00:42.846621+00",
      "chamber_id": "1",
      "temperature": "77",
      "humidity": "50",
      "pH": null,
      "PPM": null,
      "height": null,
      "water": null,
      "photo": null
    },
    {
      "time": "2017-08-03 00:28:42.846621+00",
      "chamber_id": "1",
      "temperature": "77",
      "humidity": "50",
      "pH": null,
      "PPM": null,
      "height": null,
      "water": null,
      "photo": null
    },
    {
      "time": "2017-08-03 00:56:42.846621+00",
      "chamber_id": "1",
      "temperature": "77",
      "humidity": "50",
      "pH": null,
      "PPM": null,
      "height": null,
      "water": null,
      "photo": null
    },
    {
      "time": "2017-08-03 01:24:42.846621+00",
      "chamber_id": "1",
      "temperature": "77",
      "humidity": "50",
      "pH": null,
      "PPM": null,
      "height": null,
      "water": null,
      "photo": null
    },
    {
      "time": "2017-08-03 01:52:42.846621+00",
      "chamber_id": "1",
      "temperature": "77",
      "humidity": "50",
      "pH": null,
      "PPM": null,
      "height": null,
      "water": null,
      "photo": null
    },
    {
      "time": "2017-08-03 02:20:42.846621+00",
      "chamber_id": "1",
      "temperature": "77",
      "humidity": "50",
      "pH": null,
      "PPM": null,
      "height": null,
      "water": null,
      "photo": null
    },
    {
      "time": "2017-08-03 02:48:42.846621+00",
      "chamber_id": "1",
      "temperature": "77",
      "humidity": "50",
      "pH": null,
      "PPM": null,
      "height": null,
      "water": null,
      "photo": null
    },
    {
      "time": "2017-08-03 03:16:42.846621+00",
      "chamber_id": "1",
      "temperature": "77",
      "humidity": "50",
      "pH": null,
      "PPM": null,
      "height": null,
      "water": null,
      "photo": null
    },
    {
      "time": "2017-08-03 03:16:42.846621+00",
      "chamber_id": "1",
      "temperature": "77",
      "humidity": "50",
      "pH": null,
      "PPM": null,
      "height": null,
      "water": null,
      "photo": null
    },
    {
      "time": "2017-08-03 03:44:42.846621+00",
      "chamber_id": "1",
      "temperature": "77",
      "humidity": "50",
      "pH": null,
      "PPM": null,
      "height": null,
      "water": null,
      "photo": null
    },
    {
      "time": "2017-08-03 04:12:42.846621+00",
      "chamber_id": "1",
      "temperature": "77",
      "humidity": "50",
      "pH": null,
      "PPM": null,
      "height": null,
      "water": null,
      "photo": null
    },
    {
      "time": "2017-08-03 04:40:42.846621+00",
      "chamber_id": "1",
      "temperature": "77",
      "humidity": "50",
      "pH": null,
      "PPM": null,
      "height": null,
      "water": null,
      "photo": null
    },
    {
      "time": "2017-08-03 05:08:42.846621+00",
      "chamber_id": "1",
      "temperature": "77",
      "humidity": "50",
      "pH": null,
      "PPM": null,
      "height": null,
      "water": null,
      "photo": null
    },
    {
      "time": "2017-08-03 05:36:42.846621+00",
      "chamber_id": "1",
      "temperature": "77",
      "humidity": "50",
      "pH": null,
      "PPM": null,
      "height": null,
      "water": null,
      "photo": null
    },
    {
      "time": "2017-08-03 06:04:42.846621+00",
      "chamber_id": "1",
      "temperature": "77",
      "humidity": "50",
      "pH": null,
      "PPM": null,
      "height": null,
      "water": null,
      "photo": null
    },
    {
      "time": "2017-08-03 06:32:42.846621+00",
      "chamber_id": "1",
      "temperature": "77",
      "humidity": "50",
      "pH": null,
      "PPM": null,
      "height": null,
      "water": null,
      "photo": null
    },
    {
      "time": "2017-08-03 07:00:42.846621+00",
      "chamber_id": "1",
      "temperature": "77",
      "humidity": "50",
      "pH": null,
      "PPM": null,
      "height": null,
      "water": null,
      "photo": null
    },
    {
      "time": "2017-08-03 07:28:42.846621+00",
      "chamber_id": "1",
      "temperature": "77",
      "humidity": "50",
      "pH": null,
      "PPM": null,
      "height": null,
      "water": null,
      "photo": null
    },
    {
      "time": "2017-08-03 07:56:42.846621+00",
      "chamber_id": "1",
      "temperature": "77",
      "humidity": "50",
      "pH": null,
      "PPM": null,
      "height": null,
      "water": null,
      "photo": null
    },
    {
      "time": "2017-08-03 08:24:42.846621+00",
      "chamber_id": "1",
      "temperature": "77",
      "humidity": "50",
      "pH": null,
      "PPM": null,
      "height": null,
      "water": null,
      "photo": null
    },
    {
      "time": "2017-08-03 08:52:42.846621+00",
      "chamber_id": "1",
      "temperature": "77",
      "humidity": "50",
      "pH": null,
      "PPM": null,
      "height": null,
      "water": null,
      "photo": null
    },
    {
      "time": "2017-08-03 09:20:42.846621+00",
      "chamber_id": "1",
      "temperature": "77",
      "humidity": "50",
      "pH": null,
      "PPM": null,
      "height": null,
      "water": null,
      "photo": null
    },
    {
      "time": "2017-08-03 09:48:42.846621+00",
      "chamber_id": "1",
      "temperature": "77",
      "humidity": "50",
      "pH": null,
      "PPM": null,
      "height": null,
      "water": null,
      "photo": null
    },
    {
      "time": "2017-08-03 10:00:00.846621+00",
      "chamber_id": "1",
      "temperature": "74",
      "humidity": "50",
      "pH": "5.9",
      "PPM": "350",
      "height": null,
      "water": null,
      "photo": "na"
    },
    {
      "time": "2017-08-03 10:28:42.846621+00",
      "chamber_id": "1",
      "temperature": "75",
      "humidity": "50",
      "pH": null,
      "PPM": null,
      "height": null,
      "water": null,
      "photo": null
    },
    {
      "time": "2017-08-03 10:56:42.846621+00",
      "chamber_id": "1",
      "temperature": "75",
      "humidity": "50",
      "pH": null,
      "PPM": null,
      "height": null,
      "water": null,
      "photo": null
    },
    {
      "time": "2017-08-03 11:24:42.846621+00",
      "chamber_id": "1",
      "temperature": "75",
      "humidity": "50",
      "pH": null,
      "PPM": null,
      "height": null,
      "water": null,
      "photo": null
    },
    {
      "time": "2017-08-03 11:52:42.846621+00",
      "chamber_id": "1",
      "temperature": "78",
      "humidity": "50",
      "pH": null,
      "PPM": null,
      "height": null,
      "water": null,
      "photo": null
    },
    {
      "time": "2017-08-03 12:20:42.846621+00",
      "chamber_id": "1",
      "temperature": "77",
      "humidity": "50",
      "pH": null,
      "PPM": null,
      "height": null,
      "water": null,
      "photo": null
    },
    {
      "time": "2017-08-03 12:48:42.846621+00",
      "chamber_id": "1",
      "temperature": "77",
      "humidity": "50",
      "pH": null,
      "PPM": null,
      "height": null,
      "water": null,
      "photo": null
    },
    {
      "time": "2017-08-03 13:16:42.846621+00",
      "chamber_id": "1",
      "temperature": "77",
      "humidity": "50",
      "pH": null,
      "PPM": null,
      "height": null,
      "water": null,
      "photo": null
    },
    {
      "time": "2017-08-03 13:44:42.846621+00",
      "chamber_id": "1",
      "temperature": "77",
      "humidity": "50",
      "pH": null,
      "PPM": null,
      "height": null,
      "water": null,
      "photo": null
    },
    {
      "time": "2017-08-03 14:12:42.846621+00",
      "chamber_id": "1",
      "temperature": "77",
      "humidity": "50",
      "pH": null,
      "PPM": null,
      "height": null,
      "water": null,
      "photo": null
    },
    {
      "time": "2017-08-03 14:40:42.846621+00",
      "chamber_id": "1",
      "temperature": "77",
      "humidity": "50",
      "pH": null,
      "PPM": null,
      "height": null,
      "water": null,
      "photo": null
    },
    {
      "time": "2017-08-03 15:08:42.846621+00",
      "chamber_id": "1",
      "temperature": "77",
      "humidity": "50",
      "pH": null,
      "PPM": null,
      "height": null,
      "water": null,
      "photo": null
    },
    {
      "time": "2017-08-03 15:08:42.846621+00",
      "chamber_id": "1",
      "temperature": "77",
      "humidity": "50",
      "pH": null,
      "PPM": null,
      "height": null,
      "water": null,
      "photo": null
    },
    {
      "time": "2017-08-03 15:36:42.846621+00",
      "chamber_id": "1",
      "temperature": "77",
      "humidity": "50",
      "pH": null,
      "PPM": null,
      "height": null,
      "water": null,
      "photo": null
    },
    {
      "time": "2017-08-03 16:04:42.846621+00",
      "chamber_id": "1",
      "temperature": "77",
      "humidity": "50",
      "pH": "5.8",
      "PPM": null,
      "height": null,
      "water": null,
      "photo": "na"
    },
    {
      "time": "2017-08-03 16:32:42.846621+00",
      "chamber_id": "1",
      "temperature": "77",
      "humidity": "50",
      "pH": null,
      "PPM": null,
      "height": null,
      "water": null,
      "photo": null
    },
    {
      "time": "2017-08-03 17:00:42.846621+00",
      "chamber_id": "1",
      "temperature": "77",
      "humidity": "50",
      "pH": null,
      "PPM": null,
      "height": null,
      "water": null,
      "photo": null
    },
    {
      "time": "2017-08-03 17:28:42.846621+00",
      "chamber_id": "1",
      "temperature": "77",
      "humidity": "50",
      "pH": null,
      "PPM": null,
      "height": null,
      "water": null,
      "photo": null
    },
    {
      "time": "2017-08-03 17:56:42.846621+00",
      "chamber_id": "1",
      "temperature": "77",
      "humidity": "50",
      "pH": null,
      "PPM": null,
      "height": null,
      "water": null,
      "photo": null
    },
    {
      "time": "2017-08-03 18:24:42.846621+00",
      "chamber_id": "1",
      "temperature": "77",
      "humidity": "50",
      "pH": null,
      "PPM": null,
      "height": null,
      "water": null,
      "photo": null
    },
    {
      "time": "2017-08-03 18:52:42.846621+00",
      "chamber_id": "1",
      "temperature": "77",
      "humidity": "50",
      "pH": null,
      "PPM": null,
      "height": null,
      "water": null,
      "photo": null
    },
    {
      "time": "2017-08-03 19:20:42.846621+00",
      "chamber_id": "1",
      "temperature": "73",
      "humidity": "50",
      "pH": null,
      "PPM": null,
      "height": null,
      "water": null,
      "photo": null
    },
    {
      "time": "2017-08-03 19:48:42.846621+00",
      "chamber_id": "1",
      "temperature": "74",
      "humidity": "50",
      "pH": null,
      "PPM": null,
      "height": null,
      "water": null,
      "photo": null
    },
    {
      "time": "2017-08-03 20:16:42.846621+00",
      "chamber_id": "1",
      "temperature": "77",
      "humidity": "50",
      "pH": null,
      "PPM": null,
      "height": null,
      "water": null,
      "photo": null
    },
    {
      "time": "2017-08-03 20:44:42.846621+00",
      "chamber_id": "1",
      "temperature": "77",
      "humidity": "50",
      "pH": null,
      "PPM": null,
      "height": null,
      "water": null,
      "photo": null
    },
    {
      "time": "2017-08-03 21:12:42.846621+00",
      "chamber_id": "1",
      "temperature": "77",
      "humidity": "50",
      "pH": null,
      "PPM": null,
      "height": null,
      "water": null,
      "photo": null
    },
    {
      "time": "2017-08-03 21:40:42.846621+00",
      "chamber_id": "1",
      "temperature": "77",
      "humidity": "50",
      "pH": null,
      "PPM": null,
      "height": null,
      "water": null,
      "photo": null
    },
    {
      "time": "2017-08-03 22:08:42.846621+00",
      "chamber_id": "1",
      "temperature": "77",
      "humidity": "50",
      "pH": null,
      "PPM": null,
      "height": null,
      "water": null,
      "photo": null
    },
    {
      "time": "2017-08-03 22:36:42.846621+00",
      "chamber_id": "1",
      "temperature": "77",
      "humidity": "50",
      "pH": null,
      "PPM": null,
      "height": null,
      "water": null,
      "photo": null
    },
    {
      "time": "2017-08-03 23:04:42.846621+00",
      "chamber_id": "1",
      "temperature": "77",
      "humidity": "50",
      "pH": null,
      "PPM": null,
      "height": null,
      "water": null,
      "photo": null
    },
    {
      "time": "2017-08-03 23:32:42.846621+00",
      "chamber_id": "1",
      "temperature": "77",
      "humidity": "50",
      "pH": null,
      "PPM": null,
      "height": null,
      "water": null,
      "photo": null
    }
  ],
  "chambers": [
    {
      "id": "1",
      "filled": null
    },
    {
      "id": "2",
      "filled": null
    },
    {
      "id": "3",
      "filled": null
    }
  ]
}
